[
  {
    "linkedInUrl": "https://www.linkedin.com/in/aycwong",
    "id": "c843dd45-c2ed-455f-9843-6348d8604916",
    "data": true
  },
  {
    "linkedInUrl": "https://www.linkedin.com/in/hwcbyrd",
    "id": "5a540328-809b-44f1-a015-514e246aff77",
    "data": true
  },
  {
    "linkedInUrl": "https://www.linkedin.com/in/henry-kwok-9537381",
    "id": "b39bc1d7-0676-4375-9c36-f672b310c7a8",
    "data": true
  },
  {
    "linkedInUrl": "https://www.linkedin.com/in/ctregan",
    "id": "0f6b6913-c1f1-4137-8b93-6eb9f7a586dd",
    "data": true
  },
  {
    "linkedInUrl": "https://www.linkedin.com/in/shruti-padmanabha",
    "id": "ab36a759-b3ce-43ae-81ab-f13cb772f6d3",
    "data": true
  },
  {
    "linkedInUrl": "https://www.linkedin.com/in/waloeiii",
    "id": "bb1fecdc-9e13-41e4-9316-f04ba3dec295",
    "data": true
  },
  {
    "linkedInUrl": "https://www.linkedin.com/in/toddhollmann",
    "id": "b6d01110-9404-42a0-b451-f355ee100215",
    "data": true
  },
  {
    "linkedInUrl": "https://www.linkedin.com/in/pmatthies",
    "id": "feeaf2db-cea1-4a73-9816-f8a01db3a016",
    "data": true
  },
  {
    "linkedInUrl": "https://www.linkedin.com/in/kris-boston-12588b86",
    "id": "77319b78-c05f-45f0-8c5d-dbee3847f93c",
    "data": true
  },
  {
    "linkedInUrl": "https://www.linkedin.com/in/federation",
    "id": "1c180010-ffa1-41bc-a90d-62478e3bceff",
    "data": true
  },
  {
    "linkedInUrl": "https://www.linkedin.com/in/bryanosullivan",
    "id": "8c6514bb-d4ab-4c0c-a0b5-629768850a93",
    "data": true
  },
  {
    "linkedInUrl": "https://www.linkedin.com/in/amitsangani",
    "id": "80efc370-d47e-4502-bfd2-eaa8c045fbd9",
    "data": true
  },
  {
    "linkedInUrl": "https://www.linkedin.com/in/mattsteiner",
    "id": "55d53c9e-5c0b-4915-a509-74dee325c0d6",
    "data": true
  },
  {
    "linkedInUrl": "https://www.linkedin.com/in/vishal-parekh-6a362865",
    "id": "0c5de721-3d25-49aa-8e01-755e6b21806e",
    "data": true
  },
  {
    "linkedInUrl": "https://www.linkedin.com/in/thawan-kooburat",
    "id": "9c70c55f-947f-4b28-a9dd-fecef31d652e",
    "data": true
  },
  {
    "linkedInUrl": "https://www.linkedin.com/in/lachlanmulcahy",
    "id": "ff7214d6-c021-4e4c-8c3f-4cc75db09ed4",
    "data": true
  },
  {
    "linkedInUrl": "https://www.linkedin.com/in/ankitag",
    "id": "73895560-3aec-4131-a379-04b206ee65fb",
    "data": true
  },
  {
    "linkedInUrl": "https://www.linkedin.com/in/ng1704",
    "id": "1560f68b-0656-4a12-9ba0-d84c1ae1a88e",
    "data": true
  },
  {
    "linkedInUrl": "https://www.linkedin.com/in/barracel",
    "id": "dfbfaefc-e3ae-48e7-a945-639d82c47b93",
    "data": true
  },
  {
    "linkedInUrl": "https://www.linkedin.com/in/yongbae",
    "id": "8d746f4b-7857-4f46-8565-a41a9fbcf515",
    "data": true
  },
  {
    "linkedInUrl": "https://www.linkedin.com/in/laurentcharignon",
    "id": "ac1c77ab-b7b8-4b41-83ac-b841629a9dc6",
    "data": true
  },
  {
    "linkedInUrl": "https://www.linkedin.com/in/brockamer",
    "id": "30d5fea3-545b-4159-bf6f-a48d4d394771",
    "data": true
  },
  {
    "linkedInUrl": "https://www.linkedin.com/in/hany-morsy-949691232",
    "id": "359b5f4d-824a-4943-8575-1ad114cd19a2",
    "data": true
  },
  {
    "linkedInUrl": "https://www.linkedin.com/in/marquis-thomas-94033574",
    "id": "0c569114-40b2-4273-9bd9-24dae9731788",
    "data": true
  },
  {
    "linkedInUrl": "https://www.linkedin.com/in/blakebnc",
    "id": "512e8b99-1c9f-4aa6-8393-eb7fb931b307",
    "data": true
  },
  {
    "linkedInUrl": "https://www.linkedin.com/in/danielhlee",
    "id": "6adf4cc9-caaf-41c2-b301-f3a83d15f95c",
    "data": true
  },
  {
    "linkedInUrl": "https://www.linkedin.com/in/michael-abbott-a42b358a",
    "id": "42f1189a-4377-4c92-9b3a-99131f468995",
    "data": true
  },
  {
    "linkedInUrl": "https://www.linkedin.com/in/elisalou",
    "id": "09c3fad8-c47f-4fec-9756-c0c802ec0741",
    "data": true
  },
  {
    "linkedInUrl": "https://www.linkedin.com/in/ramosjohnny",
    "id": "287425c1-769a-444c-acc7-ce02fa697a7b",
    "data": true
  }
]